{"version":1,"resource":"file:///home/ahmedsat/golang/erp-reports/main.go","entries":[{"id":"eKJr.go","timestamp":1716361111184},{"id":"pOJc.go","timestamp":1716362008632},{"id":"a9fz.go","timestamp":1716362020444},{"id":"8VuN.go","timestamp":1716362036884},{"id":"qPQS.go","timestamp":1716362344572},{"id":"Bojv.go","timestamp":1716362354672},{"id":"EYdd.go","timestamp":1716363667156},{"id":"6DNY.go","timestamp":1716363741600},{"id":"0KRO.go","timestamp":1716363823608},{"id":"L25b.go","timestamp":1716363887440},{"id":"CYp2.go","timestamp":1716363926424},{"id":"hWfu.go","timestamp":1716364128708},{"id":"u6A3.go","timestamp":1716364163008},{"id":"yuvS.go","timestamp":1716364267616},{"id":"UzeZ.go","source":"Organize Imports","timestamp":1716364270660},{"id":"Oo9n.go","timestamp":1716364291560},{"id":"68z9.go","timestamp":1716365683684},{"id":"gGbj.go","timestamp":1716365708580},{"id":"1SqP.go","timestamp":1716367499581},{"id":"nE35.go","timestamp":1716367671941},{"id":"XFzB.go","timestamp":1716367716905},{"id":"sQtB.go","timestamp":1716367873997},{"id":"YY6y.go","timestamp":1716368251209},{"id":"xGzr.go","timestamp":1716368261473},{"id":"WqvJ.go","timestamp":1716368312633},{"id":"rvCs.go","timestamp":1716368323345},{"id":"eqeR.go","timestamp":1716368439657},{"id":"Niv1.go","timestamp":1716368829869},{"id":"9Pqo.go","timestamp":1716368847541},{"id":"nBKn.go","timestamp":1716368891337},{"id":"T8g5.go","timestamp":1716369153049},{"id":"YTEy.go","timestamp":1716369182961},{"id":"Lk7x.go","timestamp":1716369289505}]}